{"published": "Sunday, February 19, 2023 6:00PM", "expires": "Monday, February 20, 2023 6:00PM", "url": "http://www.nwac.us/avalanche-forecast/#/west-slopes-north", "name": "NWAC", "danger": [{"valid_day": "Monday, February 20, 2023", "lower_num": 3, "lower_name": "Considerable", "middle_num": 4, "middle_name": "High", "upper_num": 4, "upper_name": "High"}, {"valid_day": "Tuesday, February 21, 2023", "lower_num": 3, "lower_name": "Considerable", "middle_num": 3, "middle_name": "Considerable", "upper_num": 3, "upper_name": "Considerable"}]}