{"published": "Saturday, April 08, 2023 5:30PM", "expires": "Sunday, April 09, 2023 5:30PM", "url": "http://www.nwac.us/avalanche-forecast/#/east-slopes-north", "name": "NWAC", "danger": [{"valid_day": "Sunday, April 09, 2023", "lower_num": 3, "lower_name": "Considerable", "middle_num": 3, "middle_name": "Considerable", "upper_num": 3, "upper_name": "Considerable"}, {"valid_day": "Monday, April 10, 2023", "lower_num": 3, "lower_name": "Considerable", "middle_num": 3, "middle_name": "Considerable", "upper_num": 3, "upper_name": "Considerable"}]}